videosdk/plugins/papla/__init__.py
videosdk/plugins/papla/tts.py
videosdk/plugins/papla/version.py
videosdk_plugins_papla-0.0.58.dist-info/METADATA
videosdk_plugins_papla-0.0.58.dist-info/WHEEL
videosdk_plugins_papla-0.0.58.dist-info/RECORD
